<?xml version="1.0" encoding="UTF-8"?>
<model type="decision" trigger="a_u">

<rule id="allnegs-decision">
<case>
<effect util="-10">
<set var="a_m" value="Do(*)" />
</effect>
<effect util="-2">
<set var="a_m" value="Say(*)" />
</effect>
<effect util="-2">
<set var="a_m" value="Describe(*)" />
</effect>
<effect util="-2">
<set var="a_m" value="AskRepeat" />
</effect>
<effect util="-2">
<set var="a_m" value="Confirm(*)" />
</effect>
</case>
</rule>

<rule>
<case>
<condition>
<if var="i_u" value="Move(Left)"/>
<if var="perceived" value="[]"/>
<if var="carried" value="[]" relation="!="/>
</condition>
<effect util="theta(i_u=move(left)^perceived=nothing^carried=yes)">
<set var="a_m" value="Do(Move(Left))"/>
</effect>
<effect util="theta(i_u=move(left)^perceived=nothing^carried=yes^a_m=Confirm)">
<set var="a_m" value="Confirm({i_u})"/>
</effect>
</case>
<case>
<condition>
<if var="i_u" value="Move(Left)"/>
<if var="perceived" value="[]"/>
<if var="carried" value="[]"/>
</condition>
<effect util="theta(i_u=move(left)^perceived=nothing^carried=no)">
<set var="a_m" value="Do(Move(Left))"/>
</effect>
<effect util="theta(i_u=move(left)^perceived=nothing^carried=no^a_m=Confirm)">
<set var="a_m" value="Confirm({i_u})"/>
</effect>
</case>
<case>
<condition>
<if var="i_u" value="Move(Left)"/>
<if var="perceived" value="RedObj" relation="in"/>
<if var="carried" value="[]" relation="!="/>
</condition>
<effect util="theta(i_u=move(left)^perceived=redobj^carried=yes)">
<set var="a_m" value="Do(Move(Left))"/>
</effect>
<effect util="theta(i_u=move(left)^perceived=redobj^carried=yes^a_m=Confirm)">
<set var="a_m" value="Confirm({i_u})"/>
</effect>
</case>
<case>
<condition>
<if var="i_u" value="Move(Left)"/>
<if var="perceived" value="RedObj" relation="in"/>
<if var="carried" value="[]"/>
</condition>
<effect util="theta(i_u=move(left)^perceived=redobj^carried=no)">
<set var="a_m" value="Do(Move(Left))"/>
</effect>
<effect util="theta(i_u=move(left)^perceived=redobj^carried=no^a_m=Confirm)">
<set var="a_m" value="Confirm({i_u})"/>
</effect>
</case>
<case>
<condition>
<if var="i_u" value="Move(Left)"/>
<if var="perceived" value="BlueObj" relation="in"/>
<if var="carried" value="[]" relation="!="/>
</condition>
<effect util="theta(i_u=move(left)^perceived=blueobj^carried=yes)">
<set var="a_m" value="Do(Move(Left))"/>
</effect>
<effect util="theta(i_u=move(left)^perceived=blueobj^carried=yes^a_m=Confirm)">
<set var="a_m" value="Confirm({i_u})"/>
</effect>
</case>
<case>
<condition>
<if var="i_u" value="Move(Left)"/>
<if var="perceived" value="BlueObj" relation="in"/>
<if var="carried" value="[]"/>
</condition>
<effect util="theta(i_u=move(left)^perceived=blueobj^carried=no)">
<set var="a_m" value="Do(Move(Left))"/>
</effect>
<effect util="theta(i_u=move(left)^perceived=blueobj^carried=no^a_m=Confirm)">
<set var="a_m" value="Confirm({i_u})"/>
</effect>
</case>
<case>
<condition>
<if var="i_u" value="Move(Right)"/>
<if var="perceived" value="[]"/>
<if var="carried" value="[]" relation="!="/>
</condition>
<effect util="theta(i_u=move(right)^perceived=nothing^carried=yes)">
<set var="a_m" value="Do(Move(Right))"/>
</effect>
<effect util="theta(i_u=move(right)^perceived=nothing^carried=yes^a_m=Confirm)">
<set var="a_m" value="Confirm({i_u})"/>
</effect>
</case>
<case>
<condition>
<if var="i_u" value="Move(Right)"/>
<if var="perceived" value="[]"/>
<if var="carried" value="[]"/>
</condition>
<effect util="theta(i_u=move(right)^perceived=nothing^carried=no)">
<set var="a_m" value="Do(Move(Right))"/>
</effect>
<effect util="theta(i_u=move(right)^perceived=nothing^carried=no^a_m=Confirm)">
<set var="a_m" value="Confirm({i_u})"/>
</effect>
</case>
<case>
<condition>
<if var="i_u" value="Move(Right)"/>
<if var="perceived" value="RedObj" relation="in"/>
<if var="carried" value="[]" relation="!="/>
</condition>
<effect util="theta(i_u=move(right)^perceived=redobj^carried=yes)">
<set var="a_m" value="Do(Move(Right))"/>
</effect>
<effect util="theta(i_u=move(right)^perceived=redobj^carried=yes^a_m=Confirm)">
<set var="a_m" value="Confirm({i_u})"/>
</effect>
</case>
<case>
<condition>
<if var="i_u" value="Move(Right)"/>
<if var="perceived" value="RedObj" relation="in"/>
<if var="carried" value="[]"/>
</condition>
<effect util="theta(i_u=move(right)^perceived=redobj^carried=no)">
<set var="a_m" value="Do(Move(Right))"/>
</effect>
<effect util="theta(i_u=move(right)^perceived=redobj^carried=no^a_m=Confirm)">
<set var="a_m" value="Confirm({i_u})"/>
</effect>
</case>
<case>
<condition>
<if var="i_u" value="Move(Right)"/>
<if var="perceived" value="BlueObj" relation="in"/>
<if var="carried" value="[]" relation="!="/>
</condition>
<effect util="theta(i_u=move(right)^perceived=blueobj^carried=yes)">
<set var="a_m" value="Do(Move(Right))"/>
</effect>
<effect util="theta(i_u=move(right)^perceived=blueobj^carried=yes^a_m=Confirm)">
<set var="a_m" value="Confirm({i_u})"/>
</effect>
</case>
<case>
<condition>
<if var="i_u" value="Move(Right)"/>
<if var="perceived" value="BlueObj" relation="in"/>
<if var="carried" value="[]"/>
</condition>
<effect util="theta(i_u=move(right)^perceived=blueobj^carried=no)">
<set var="a_m" value="Do(Move(Right))"/>
</effect>
<effect util="theta(i_u=move(right)^perceived=blueobj^carried=no^a_m=Confirm)">
<set var="a_m" value="Confirm({i_u})"/>
</effect>
</case>
<case>
<condition>
<if var="i_u" value="Move(Forward)"/>
<if var="perceived" value="[]"/>
<if var="carried" value="[]" relation="!="/>
</condition>
<effect util="theta(i_u=move(forward)^perceived=nothing^carried=yes)">
<set var="a_m" value="Do(Move(Forward))"/>
</effect>
<effect util="theta(i_u=move(forward)^perceived=nothing^carried=yes^a_m=Confirm)">
<set var="a_m" value="Confirm({i_u})"/>
</effect>
</case>
<case>
<condition>
<if var="i_u" value="Move(Forward)"/>
<if var="perceived" value="[]"/>
<if var="carried" value="[]"/>
</condition>
<effect util="theta(i_u=move(forward)^perceived=nothing^carried=no)">
<set var="a_m" value="Do(Move(Forward))"/>
</effect>
<effect util="theta(i_u=move(forward)^perceived=nothing^carried=no^a_m=Confirm)">
<set var="a_m" value="Confirm({i_u})"/>
</effect>
</case>
<case>
<condition>
<if var="i_u" value="Move(Forward)"/>
<if var="perceived" value="RedObj" relation="in"/>
<if var="carried" value="[]" relation="!="/>
</condition>
<effect util="theta(i_u=move(forward)^perceived=redobj^carried=yes)">
<set var="a_m" value="Do(Move(Forward))"/>
</effect>
<effect util="theta(i_u=move(forward)^perceived=redobj^carried=yes^a_m=Confirm)">
<set var="a_m" value="Confirm({i_u})"/>
</effect>
</case>
<case>
<condition>
<if var="i_u" value="Move(Forward)"/>
<if var="perceived" value="RedObj" relation="in"/>
<if var="carried" value="[]"/>
</condition>
<effect util="theta(i_u=move(forward)^perceived=redobj^carried=no)">
<set var="a_m" value="Do(Move(Forward))"/>
</effect>
<effect util="theta(i_u=move(forward)^perceived=redobj^carried=no^a_m=Confirm)">
<set var="a_m" value="Confirm({i_u})"/>
</effect>
</case>
<case>
<condition>
<if var="i_u" value="Move(Forward)"/>
<if var="perceived" value="BlueObj" relation="in"/>
<if var="carried" value="[]" relation="!="/>
</condition>
<effect util="theta(i_u=move(forward)^perceived=blueobj^carried=yes)">
<set var="a_m" value="Do(Move(Forward))"/>
</effect>
<effect util="theta(i_u=move(forward)^perceived=blueobj^carried=yes^a_m=Confirm)">
<set var="a_m" value="Confirm({i_u})"/>
</effect>
</case>
<case>
<condition>
<if var="i_u" value="Move(Forward)"/>
<if var="perceived" value="BlueObj" relation="in"/>
<if var="carried" value="[]"/>
</condition>
<effect util="theta(i_u=move(forward)^perceived=blueobj^carried=no)">
<set var="a_m" value="Do(Move(Forward))"/>
</effect>
<effect util="theta(i_u=move(forward)^perceived=blueobj^carried=no^a_m=Confirm)">
<set var="a_m" value="Confirm({i_u})"/>
</effect>
</case>
<case>
<condition>
<if var="i_u" value="Move(Backward)"/>
<if var="perceived" value="[]"/>
<if var="carried" value="[]" relation="!="/>
</condition>
<effect util="theta(i_u=move(backward)^perceived=nothing^carried=yes)">
<set var="a_m" value="Do(Move(Backward))"/>
</effect>
<effect util="theta(i_u=move(backward)^perceived=nothing^carried=yes^a_m=Confirm)">
<set var="a_m" value="Confirm({i_u})"/>
</effect>
</case>
<case>
<condition>
<if var="i_u" value="Move(Backward)"/>
<if var="perceived" value="[]"/>
<if var="carried" value="[]"/>
</condition>
<effect util="theta(i_u=move(backward)^perceived=nothing^carried=no)">
<set var="a_m" value="Do(Move(Backward))"/>
</effect>
<effect util="theta(i_u=move(backward)^perceived=nothing^carried=no^a_m=Confirm)">
<set var="a_m" value="Confirm({i_u})"/>
</effect>
</case>
<case>
<condition>
<if var="i_u" value="Move(Backward)"/>
<if var="perceived" value="RedObj" relation="in"/>
<if var="carried" value="[]" relation="!="/>
</condition>
<effect util="theta(i_u=move(backward)^perceived=redobj^carried=yes)">
<set var="a_m" value="Do(Move(Backward))"/>
</effect>
<effect util="theta(i_u=move(backward)^perceived=redobj^carried=yes^a_m=Confirm)">
<set var="a_m" value="Confirm({i_u})"/>
</effect>
</case>
<case>
<condition>
<if var="i_u" value="Move(Backward)"/>
<if var="perceived" value="RedObj" relation="in"/>
<if var="carried" value="[]"/>
</condition>
<effect util="theta(i_u=move(backward)^perceived=redobj^carried=no)">
<set var="a_m" value="Do(Move(Backward))"/>
</effect>
<effect util="theta(i_u=move(backward)^perceived=redobj^carried=no^a_m=Confirm)">
<set var="a_m" value="Confirm({i_u})"/>
</effect>
</case>
<case>
<condition>
<if var="i_u" value="Move(Backward)"/>
<if var="perceived" value="BlueObj" relation="in"/>
<if var="carried" value="[]" relation="!="/>
</condition>
<effect util="theta(i_u=move(backward)^perceived=blueobj^carried=yes)">
<set var="a_m" value="Do(Move(Backward))"/>
</effect>
<effect util="theta(i_u=move(backward)^perceived=blueobj^carried=yes^a_m=Confirm)">
<set var="a_m" value="Confirm({i_u})"/>
</effect>
</case>
<case>
<condition>
<if var="i_u" value="Move(Backward)"/>
<if var="perceived" value="BlueObj" relation="in"/>
<if var="carried" value="[]"/>
</condition>
<effect util="theta(i_u=move(backward)^perceived=blueobj^carried=no)">
<set var="a_m" value="Do(Move(Backward))"/>
</effect>
<effect util="theta(i_u=move(backward)^perceived=blueobj^carried=no^a_m=Confirm)">
<set var="a_m" value="Confirm({i_u})"/>
</effect>
</case>
<case>
<condition>
<if var="i_u" value="Move(Turn)"/>
<if var="perceived" value="[]"/>
<if var="carried" value="[]" relation="!="/>
</condition>
<effect util="theta(i_u=move(turn)^perceived=nothing^carried=yes)">
<set var="a_m" value="Do(Move(Turn))"/>
</effect>
<effect util="theta(i_u=move(turn)^perceived=nothing^carried=yes^a_m=Confirm)">
<set var="a_m" value="Confirm({i_u})"/>
</effect>
</case>
<case>
<condition>
<if var="i_u" value="Move(Turn)"/>
<if var="perceived" value="[]"/>
<if var="carried" value="[]"/>
</condition>
<effect util="theta(i_u=move(turn)^perceived=nothing^carried=no)">
<set var="a_m" value="Do(Move(Turn))"/>
</effect>
<effect util="theta(i_u=move(turn)^perceived=nothing^carried=no^a_m=Confirm)">
<set var="a_m" value="Confirm({i_u})"/>
</effect>
</case>
<case>
<condition>
<if var="i_u" value="Move(Turn)"/>
<if var="perceived" value="RedObj" relation="in"/>
<if var="carried" value="[]" relation="!="/>
</condition>
<effect util="theta(i_u=move(turn)^perceived=redobj^carried=yes)">
<set var="a_m" value="Do(Move(Turn))"/>
</effect>
<effect util="theta(i_u=move(turn)^perceived=redobj^carried=yes^a_m=Confirm)">
<set var="a_m" value="Confirm({i_u})"/>
</effect>
</case>
<case>
<condition>
<if var="i_u" value="Move(Turn)"/>
<if var="perceived" value="RedObj" relation="in"/>
<if var="carried" value="[]"/>
</condition>
<effect util="theta(i_u=move(turn)^perceived=redobj^carried=no)">
<set var="a_m" value="Do(Move(Turn))"/>
</effect>
<effect util="theta(i_u=move(turn)^perceived=redobj^carried=no^a_m=Confirm)">
<set var="a_m" value="Confirm({i_u})"/>
</effect>
</case>
<case>
<condition>
<if var="i_u" value="Move(Turn)"/>
<if var="perceived" value="BlueObj" relation="in"/>
<if var="carried" value="[]" relation="!="/>
</condition>
<effect util="theta(i_u=move(turn)^perceived=blueobj^carried=yes)">
<set var="a_m" value="Do(Move(Turn))"/>
</effect>
<effect util="theta(i_u=move(turn)^perceived=blueobj^carried=yes^a_m=Confirm)">
<set var="a_m" value="Confirm({i_u})"/>
</effect>
</case>
<case>
<condition>
<if var="i_u" value="Move(Turn)"/>
<if var="perceived" value="BlueObj" relation="in"/>
<if var="carried" value="[]"/>
</condition>
<effect util="theta(i_u=move(turn)^perceived=blueobj^carried=no)">
<set var="a_m" value="Do(Move(Turn))"/>
</effect>
<effect util="theta(i_u=move(turn)^perceived=blueobj^carried=no^a_m=Confirm)">
<set var="a_m" value="Confirm({i_u})"/>
</effect>
</case>
<case>
<condition>
<if var="i_u" value="Move(Left,Short)"/>
<if var="perceived" value="[]"/>
<if var="carried" value="[]" relation="!="/>
</condition>
<effect util="theta(i_u=move(left,short)^perceived=nothing^carried=yes)">
<set var="a_m" value="Do(Move(Left,Short))"/>
</effect>
<effect util="theta(i_u=move(left,short)^perceived=nothing^carried=yes^a_m=Confirm)">
<set var="a_m" value="Confirm({i_u})"/>
</effect>
</case>
<case>
<condition>
<if var="i_u" value="Move(Left,Short)"/>
<if var="perceived" value="[]"/>
<if var="carried" value="[]"/>
</condition>
<effect util="theta(i_u=move(left,short)^perceived=nothing^carried=no)">
<set var="a_m" value="Do(Move(Left,Short))"/>
</effect>
<effect util="theta(i_u=move(left,short)^perceived=nothing^carried=no^a_m=Confirm)">
<set var="a_m" value="Confirm({i_u})"/>
</effect>
</case>
<case>
<condition>
<if var="i_u" value="Move(Left,Short)"/>
<if var="perceived" value="RedObj" relation="in"/>
<if var="carried" value="[]" relation="!="/>
</condition>
<effect util="theta(i_u=move(left,short)^perceived=redobj^carried=yes)">
<set var="a_m" value="Do(Move(Left,Short))"/>
</effect>
<effect util="theta(i_u=move(left,short)^perceived=redobj^carried=yes^a_m=Confirm)">
<set var="a_m" value="Confirm({i_u})"/>
</effect>
</case>
<case>
<condition>
<if var="i_u" value="Move(Left,Short)"/>
<if var="perceived" value="RedObj" relation="in"/>
<if var="carried" value="[]"/>
</condition>
<effect util="theta(i_u=move(left,short)^perceived=redobj^carried=no)">
<set var="a_m" value="Do(Move(Left,Short))"/>
</effect>
<effect util="theta(i_u=move(left,short)^perceived=redobj^carried=no^a_m=Confirm)">
<set var="a_m" value="Confirm({i_u})"/>
</effect>
</case>
<case>
<condition>
<if var="i_u" value="Move(Left,Short)"/>
<if var="perceived" value="BlueObj" relation="in"/>
<if var="carried" value="[]" relation="!="/>
</condition>
<effect util="theta(i_u=move(left,short)^perceived=blueobj^carried=yes)">
<set var="a_m" value="Do(Move(Left,Short))"/>
</effect>
<effect util="theta(i_u=move(left,short)^perceived=blueobj^carried=yes^a_m=Confirm)">
<set var="a_m" value="Confirm({i_u})"/>
</effect>
</case>
<case>
<condition>
<if var="i_u" value="Move(Left,Short)"/>
<if var="perceived" value="BlueObj" relation="in"/>
<if var="carried" value="[]"/>
</condition>
<effect util="theta(i_u=move(left,short)^perceived=blueobj^carried=no)">
<set var="a_m" value="Do(Move(Left,Short))"/>
</effect>
<effect util="theta(i_u=move(left,short)^perceived=blueobj^carried=no^a_m=Confirm)">
<set var="a_m" value="Confirm({i_u})"/>
</effect>
</case>
<case>
<condition>
<if var="i_u" value="Move(Right,Short)"/>
<if var="perceived" value="[]"/>
<if var="carried" value="[]" relation="!="/>
</condition>
<effect util="theta(i_u=move(right,short)^perceived=nothing^carried=yes)">
<set var="a_m" value="Do(Move(Right,Short))"/>
</effect>
<effect util="theta(i_u=move(right,short)^perceived=nothing^carried=yes^a_m=Confirm)">
<set var="a_m" value="Confirm({i_u})"/>
</effect>
</case>
<case>
<condition>
<if var="i_u" value="Move(Right,Short)"/>
<if var="perceived" value="[]"/>
<if var="carried" value="[]"/>
</condition>
<effect util="theta(i_u=move(right,short)^perceived=nothing^carried=no)">
<set var="a_m" value="Do(Move(Right,Short))"/>
</effect>
<effect util="theta(i_u=move(right,short)^perceived=nothing^carried=no^a_m=Confirm)">
<set var="a_m" value="Confirm({i_u})"/>
</effect>
</case>
<case>
<condition>
<if var="i_u" value="Move(Right,Short)"/>
<if var="perceived" value="RedObj" relation="in"/>
<if var="carried" value="[]" relation="!="/>
</condition>
<effect util="theta(i_u=move(right,short)^perceived=redobj^carried=yes)">
<set var="a_m" value="Do(Move(Right,Short))"/>
</effect>
<effect util="theta(i_u=move(right,short)^perceived=redobj^carried=yes^a_m=Confirm)">
<set var="a_m" value="Confirm({i_u})"/>
</effect>
</case>
<case>
<condition>
<if var="i_u" value="Move(Right,Short)"/>
<if var="perceived" value="RedObj" relation="in"/>
<if var="carried" value="[]"/>
</condition>
<effect util="theta(i_u=move(right,short)^perceived=redobj^carried=no)">
<set var="a_m" value="Do(Move(Right,Short))"/>
</effect>
<effect util="theta(i_u=move(right,short)^perceived=redobj^carried=no^a_m=Confirm)">
<set var="a_m" value="Confirm({i_u})"/>
</effect>
</case>
<case>
<condition>
<if var="i_u" value="Move(Right,Short)"/>
<if var="perceived" value="BlueObj" relation="in"/>
<if var="carried" value="[]" relation="!="/>
</condition>
<effect util="theta(i_u=move(right,short)^perceived=blueobj^carried=yes)">
<set var="a_m" value="Do(Move(Right,Short))"/>
</effect>
<effect util="theta(i_u=move(right,short)^perceived=blueobj^carried=yes^a_m=Confirm)">
<set var="a_m" value="Confirm({i_u})"/>
</effect>
</case>
<case>
<condition>
<if var="i_u" value="Move(Right,Short)"/>
<if var="perceived" value="BlueObj" relation="in"/>
<if var="carried" value="[]"/>
</condition>
<effect util="theta(i_u=move(right,short)^perceived=blueobj^carried=no)">
<set var="a_m" value="Do(Move(Right,Short))"/>
</effect>
<effect util="theta(i_u=move(right,short)^perceived=blueobj^carried=no^a_m=Confirm)">
<set var="a_m" value="Confirm({i_u})"/>
</effect>
</case>
<case>
<condition>
<if var="i_u" value="Move(Forward,Short)"/>
<if var="perceived" value="[]"/>
<if var="carried" value="[]" relation="!="/>
</condition>
<effect util="theta(i_u=move(forward,short)^perceived=nothing^carried=yes)">
<set var="a_m" value="Do(Move(Forward,Short))"/>
</effect>
<effect util="theta(i_u=move(forward,short)^perceived=nothing^carried=yes^a_m=Confirm)">
<set var="a_m" value="Confirm({i_u})"/>
</effect>
</case>
<case>
<condition>
<if var="i_u" value="Move(Forward,Short)"/>
<if var="perceived" value="[]"/>
<if var="carried" value="[]"/>
</condition>
<effect util="theta(i_u=move(forward,short)^perceived=nothing^carried=no)">
<set var="a_m" value="Do(Move(Forward,Short))"/>
</effect>
<effect util="theta(i_u=move(forward,short)^perceived=nothing^carried=no^a_m=Confirm)">
<set var="a_m" value="Confirm({i_u})"/>
</effect>
</case>
<case>
<condition>
<if var="i_u" value="Move(Forward,Short)"/>
<if var="perceived" value="RedObj" relation="in"/>
<if var="carried" value="[]" relation="!="/>
</condition>
<effect util="theta(i_u=move(forward,short)^perceived=redobj^carried=yes)">
<set var="a_m" value="Do(Move(Forward,Short))"/>
</effect>
<effect util="theta(i_u=move(forward,short)^perceived=redobj^carried=yes^a_m=Confirm)">
<set var="a_m" value="Confirm({i_u})"/>
</effect>
</case>
<case>
<condition>
<if var="i_u" value="Move(Forward,Short)"/>
<if var="perceived" value="RedObj" relation="in"/>
<if var="carried" value="[]"/>
</condition>
<effect util="theta(i_u=move(forward,short)^perceived=redobj^carried=no)">
<set var="a_m" value="Do(Move(Forward,Short))"/>
</effect>
<effect util="theta(i_u=move(forward,short)^perceived=redobj^carried=no^a_m=Confirm)">
<set var="a_m" value="Confirm({i_u})"/>
</effect>
</case>
<case>
<condition>
<if var="i_u" value="Move(Forward,Short)"/>
<if var="perceived" value="BlueObj" relation="in"/>
<if var="carried" value="[]" relation="!="/>
</condition>
<effect util="theta(i_u=move(forward,short)^perceived=blueobj^carried=yes)">
<set var="a_m" value="Do(Move(Forward,Short))"/>
</effect>
<effect util="theta(i_u=move(forward,short)^perceived=blueobj^carried=yes^a_m=Confirm)">
<set var="a_m" value="Confirm({i_u})"/>
</effect>
</case>
<case>
<condition>
<if var="i_u" value="Move(Forward,Short)"/>
<if var="perceived" value="BlueObj" relation="in"/>
<if var="carried" value="[]"/>
</condition>
<effect util="theta(i_u=move(forward,short)^perceived=blueobj^carried=no)">
<set var="a_m" value="Do(Move(Forward,Short))"/>
</effect>
<effect util="theta(i_u=move(forward,short)^perceived=blueobj^carried=no^a_m=Confirm)">
<set var="a_m" value="Confirm({i_u})"/>
</effect>
</case>
<case>
<condition>
<if var="i_u" value="Move(Backward,Short)"/>
<if var="perceived" value="[]"/>
<if var="carried" value="[]" relation="!="/>
</condition>
<effect util="theta(i_u=move(backward,short)^perceived=nothing^carried=yes)">
<set var="a_m" value="Do(Move(Backward,Short))"/>
</effect>
<effect util="theta(i_u=move(backward,short)^perceived=nothing^carried=yes^a_m=Confirm)">
<set var="a_m" value="Confirm({i_u})"/>
</effect>
</case>
<case>
<condition>
<if var="i_u" value="Move(Backward,Short)"/>
<if var="perceived" value="[]"/>
<if var="carried" value="[]"/>
</condition>
<effect util="theta(i_u=move(backward,short)^perceived=nothing^carried=no)">
<set var="a_m" value="Do(Move(Backward,Short))"/>
</effect>
<effect util="theta(i_u=move(backward,short)^perceived=nothing^carried=no^a_m=Confirm)">
<set var="a_m" value="Confirm({i_u})"/>
</effect>
</case>
<case>
<condition>
<if var="i_u" value="Move(Backward,Short)"/>
<if var="perceived" value="RedObj" relation="in"/>
<if var="carried" value="[]" relation="!="/>
</condition>
<effect util="theta(i_u=move(backward,short)^perceived=redobj^carried=yes)">
<set var="a_m" value="Do(Move(Backward,Short))"/>
</effect>
<effect util="theta(i_u=move(backward,short)^perceived=redobj^carried=yes^a_m=Confirm)">
<set var="a_m" value="Confirm({i_u})"/>
</effect>
</case>
<case>
<condition>
<if var="i_u" value="Move(Backward,Short)"/>
<if var="perceived" value="RedObj" relation="in"/>
<if var="carried" value="[]"/>
</condition>
<effect util="theta(i_u=move(backward,short)^perceived=redobj^carried=no)">
<set var="a_m" value="Do(Move(Backward,Short))"/>
</effect>
<effect util="theta(i_u=move(backward,short)^perceived=redobj^carried=no^a_m=Confirm)">
<set var="a_m" value="Confirm({i_u})"/>
</effect>
</case>
<case>
<condition>
<if var="i_u" value="Move(Backward,Short)"/>
<if var="perceived" value="BlueObj" relation="in"/>
<if var="carried" value="[]" relation="!="/>
</condition>
<effect util="theta(i_u=move(backward,short)^perceived=blueobj^carried=yes)">
<set var="a_m" value="Do(Move(Backward,Short))"/>
</effect>
<effect util="theta(i_u=move(backward,short)^perceived=blueobj^carried=yes^a_m=Confirm)">
<set var="a_m" value="Confirm({i_u})"/>
</effect>
</case>
<case>
<condition>
<if var="i_u" value="Move(Backward,Short)"/>
<if var="perceived" value="BlueObj" relation="in"/>
<if var="carried" value="[]"/>
</condition>
<effect util="theta(i_u=move(backward,short)^perceived=blueobj^carried=no)">
<set var="a_m" value="Do(Move(Backward,Short))"/>
</effect>
<effect util="theta(i_u=move(backward,short)^perceived=blueobj^carried=no^a_m=Confirm)">
<set var="a_m" value="Confirm({i_u})"/>
</effect>
</case>
<case>
<condition>
<if var="i_u" value="PickUp(RedObj)"/>
<if var="perceived" value="[]"/>
<if var="carried" value="[]" relation="!="/>
</condition>
<effect util="theta(i_u=pickup(redobj)^perceived=nothing^carried=yes)">
<set var="a_m" value="Say(AlreadyCarryObject)"/>
</effect>
<effect util="theta(i_u=pickup(redobj)^perceived=nothing^carried=yes^a_m=Confirm)">
<set var="a_m" value="Confirm({i_u})"/>
</effect>
</case>
<case>
<condition>
<if var="i_u" value="PickUp(RedObj)"/>
<if var="perceived" value="[]"/>
<if var="carried" value="[]"/>
</condition>
<effect util="theta(i_u=pickup(redobj)^perceived=nothing^carried=no)">
<set var="a_m" value="Say(DoNotSeeObject)"/>
</effect>
<effect util="theta(i_u=pickup(redobj)^perceived=nothing^carried=no^a_m=Confirm)">
<set var="a_m" value="Confirm({i_u})"/>
</effect>
</case>
<case>
<condition>
<if var="i_u" value="PickUp(RedObj)"/>
<if var="perceived" value="RedObj" relation="in"/>
<if var="carried" value="[]" relation="!="/>
</condition>
<effect util="theta(i_u=pickup(redobj)^perceived=redobj^carried=yes)">
<set var="a_m" value="Say(AlreadyCarryObject)"/>
</effect>
<effect util="theta(i_u=pickup(redobj)^perceived=redobj^carried=yes^a_m=Confirm)">
<set var="a_m" value="Confirm({i_u})"/>
</effect>
</case>
<case>
<condition>
<if var="i_u" value="PickUp(RedObj)"/>
<if var="perceived" value="RedObj" relation="in"/>
<if var="carried" value="[]"/>
</condition>
<effect util="theta(i_u=pickup(redobj)^perceived=redobj^carried=no)">
<set var="a_m" value="Do(PickUp(RedObj))"/>
</effect>
<effect util="theta(i_u=pickup(redobj)^perceived=redobj^carried=no^a_m=Confirm)">
<set var="a_m" value="Confirm({i_u})"/>
</effect>
</case>
<case>
<condition>
<if var="i_u" value="PickUp(RedObj)"/>
<if var="perceived" value="BlueObj" relation="in"/>
<if var="carried" value="[]" relation="!="/>
</condition>
<effect util="theta(i_u=pickup(redobj)^perceived=blueobj^carried=yes)">
<set var="a_m" value="Say(AlreadyCarryObject)"/>
</effect>
<effect util="theta(i_u=pickup(redobj)^perceived=blueobj^carried=yes^a_m=Confirm)">
<set var="a_m" value="Confirm({i_u})"/>
</effect>
</case>
<case>
<condition>
<if var="i_u" value="PickUp(RedObj)"/>
<if var="perceived" value="BlueObj" relation="in"/>
<if var="carried" value="[]"/>
</condition>
<effect util="theta(i_u=pickup(redobj)^perceived=blueobj^carried=no)">
<set var="a_m" value="Say(DoNotSeeObject)"/>
</effect>
<effect util="theta(i_u=pickup(redobj)^perceived=blueobj^carried=no^a_m=Confirm)">
<set var="a_m" value="Confirm({i_u})"/>
</effect>
</case>
<case>
<condition>
<if var="i_u" value="PickUp(BlueObj)"/>
<if var="perceived" value="[]"/>
<if var="carried" value="[]" relation="!="/>
</condition>
<effect util="theta(i_u=pickup(blueobj)^perceived=nothing^carried=yes)">
<set var="a_m" value="Say(AlreadyCarryObject)"/>
</effect>
<effect util="theta(i_u=pickup(blueobj)^perceived=nothing^carried=yes^a_m=Confirm)">
<set var="a_m" value="Confirm({i_u})"/>
</effect>
</case>
<case>
<condition>
<if var="i_u" value="PickUp(BlueObj)"/>
<if var="perceived" value="[]"/>
<if var="carried" value="[]"/>
</condition>
<effect util="theta(i_u=pickup(blueobj)^perceived=nothing^carried=no)">
<set var="a_m" value="Say(DoNotSeeObject)"/>
</effect>
<effect util="theta(i_u=pickup(blueobj)^perceived=nothing^carried=no^a_m=Confirm)">
<set var="a_m" value="Confirm({i_u})"/>
</effect>
</case>
<case>
<condition>
<if var="i_u" value="PickUp(BlueObj)"/>
<if var="perceived" value="RedObj" relation="in"/>
<if var="carried" value="[]" relation="!="/>
</condition>
<effect util="theta(i_u=pickup(blueobj)^perceived=redobj^carried=yes)">
<set var="a_m" value="Say(AlreadyCarryObject)"/>
</effect>
<effect util="theta(i_u=pickup(blueobj)^perceived=redobj^carried=yes^a_m=Confirm)">
<set var="a_m" value="Confirm({i_u})"/>
</effect>
</case>
<case>
<condition>
<if var="i_u" value="PickUp(BlueObj)"/>
<if var="perceived" value="RedObj" relation="in"/>
<if var="carried" value="[]"/>
</condition>
<effect util="theta(i_u=pickup(blueobj)^perceived=redobj^carried=no)">
<set var="a_m" value="Say(DoNotSeeObject)"/>
</effect>
<effect util="theta(i_u=pickup(blueobj)^perceived=redobj^carried=no^a_m=Confirm)">
<set var="a_m" value="Confirm({i_u})"/>
</effect>
</case>
<case>
<condition>
<if var="i_u" value="PickUp(BlueObj)"/>
<if var="perceived" value="BlueObj" relation="in"/>
<if var="carried" value="[]" relation="!="/>
</condition>
<effect util="theta(i_u=pickup(blueobj)^perceived=blueobj^carried=yes)">
<set var="a_m" value="Say(AlreadyCarryObject)"/>
</effect>
<effect util="theta(i_u=pickup(blueobj)^perceived=blueobj^carried=yes^a_m=Confirm)">
<set var="a_m" value="Confirm({i_u})"/>
</effect>
</case>
<case>
<condition>
<if var="i_u" value="PickUp(BlueObj)"/>
<if var="perceived" value="BlueObj" relation="in"/>
<if var="carried" value="[]"/>
</condition>
<effect util="theta(i_u=pickup(blueobj)^perceived=blueobj^carried=no)">
<set var="a_m" value="Do(PickUp(BlueObj))"/>
</effect>
<effect util="theta(i_u=pickup(blueobj)^perceived=blueobj^carried=no^a_m=Confirm)">
<set var="a_m" value="Confirm({i_u})"/>
</effect>
</case>
<case>
<condition>
<if var="i_u" value="PickUp(AtFeet)"/>
<if var="perceived" value="[]"/>
<if var="carried" value="[]" relation="!="/>
</condition>
<effect util="theta(i_u=pickup(atfeet)^perceived=nothing^carried=yes)">
<set var="a_m" value="Say(AlreadyCarryObject)"/>
</effect>
<effect util="theta(i_u=pickup(atfeet)^perceived=nothing^carried=yes^a_m=Confirm)">
<set var="a_m" value="Confirm({i_u})"/>
</effect>
</case>
<case>
<condition>
<if var="i_u" value="PickUp(AtFeet)"/>
<if var="perceived" value="[]"/>
<if var="carried" value="[]"/>
</condition>
<effect util="theta(i_u=pickup(atfeet)^perceived=nothing^carried=no)">
<set var="a_m" value="Do(PickUp(AtFeet))"/>
</effect>
<effect util="theta(i_u=pickup(atfeet)^perceived=nothing^carried=no^a_m=Confirm)">
<set var="a_m" value="Confirm({i_u})"/>
</effect>
</case>
<case>
<condition>
<if var="i_u" value="PickUp(AtFeet)"/>
<if var="perceived" value="RedObj" relation="in"/>
<if var="carried" value="[]" relation="!="/>
</condition>
<effect util="theta(i_u=pickup(atfeet)^perceived=redobj^carried=yes)">
<set var="a_m" value="Say(AlreadyCarryObject)"/>
</effect>
<effect util="theta(i_u=pickup(atfeet)^perceived=redobj^carried=yes^a_m=Confirm)">
<set var="a_m" value="Confirm({i_u})"/>
</effect>
</case>
<case>
<condition>
<if var="i_u" value="PickUp(AtFeet)"/>
<if var="perceived" value="RedObj" relation="in"/>
<if var="carried" value="[]"/>
</condition>
<effect util="theta(i_u=pickup(atfeet)^perceived=redobj^carried=no)">
<set var="a_m" value="Do(PickUp(AtFeet))"/>
</effect>
<effect util="theta(i_u=pickup(atfeet)^perceived=redobj^carried=no^a_m=Confirm)">
<set var="a_m" value="Confirm({i_u})"/>
</effect>
</case>
<case>
<condition>
<if var="i_u" value="PickUp(AtFeet)"/>
<if var="perceived" value="BlueObj" relation="in"/>
<if var="carried" value="[]" relation="!="/>
</condition>
<effect util="theta(i_u=pickup(atfeet)^perceived=blueobj^carried=yes)">
<set var="a_m" value="Say(AlreadyCarryObject)"/>
</effect>
<effect util="theta(i_u=pickup(atfeet)^perceived=blueobj^carried=yes^a_m=Confirm)">
<set var="a_m" value="Confirm({i_u})"/>
</effect>
</case>
<case>
<condition>
<if var="i_u" value="PickUp(AtFeet)"/>
<if var="perceived" value="BlueObj" relation="in"/>
<if var="carried" value="[]"/>
</condition>
<effect util="theta(i_u=pickup(atfeet)^perceived=blueobj^carried=no)">
<set var="a_m" value="Do(PickUp(AtFeet))"/>
</effect>
<effect util="theta(i_u=pickup(atfeet)^perceived=blueobj^carried=no^a_m=Confirm)">
<set var="a_m" value="Confirm({i_u})"/>
</effect>
</case>
<case>
<condition>
<if var="i_u" value="Release"/>
<if var="perceived" value="[]"/>
<if var="carried" value="[]" relation="!="/>
</condition>
<effect util="theta(i_u=release^perceived=nothing^carried=yes)">
<set var="a_m" value="Do(Release)"/>
</effect>
<effect util="theta(i_u=release^perceived=nothing^carried=yes^a_m=Confirm)">
<set var="a_m" value="Confirm({i_u})"/>
</effect>
</case>
<case>
<condition>
<if var="i_u" value="Release"/>
<if var="perceived" value="[]"/>
<if var="carried" value="[]"/>
</condition>
<effect util="theta(i_u=release^perceived=nothing^carried=no)">
<set var="a_m" value="Say(DoNotCarryObject)"/>
</effect>
<effect util="theta(i_u=release^perceived=nothing^carried=no^a_m=Confirm)">
<set var="a_m" value="Confirm({i_u})"/>
</effect>
</case>
<case>
<condition>
<if var="i_u" value="Release"/>
<if var="perceived" value="RedObj" relation="in"/>
<if var="carried" value="[]" relation="!="/>
</condition>
<effect util="theta(i_u=release^perceived=redobj^carried=yes)">
<set var="a_m" value="Do(Release)"/>
</effect>
<effect util="theta(i_u=release^perceived=redobj^carried=yes^a_m=Confirm)">
<set var="a_m" value="Confirm({i_u})"/>
</effect>
</case>
<case>
<condition>
<if var="i_u" value="Release"/>
<if var="perceived" value="RedObj" relation="in"/>
<if var="carried" value="[]"/>
</condition>
<effect util="theta(i_u=release^perceived=redobj^carried=no)">
<set var="a_m" value="Say(DoNotCarryObject)"/>
</effect>
<effect util="theta(i_u=release^perceived=redobj^carried=no^a_m=Confirm)">
<set var="a_m" value="Confirm({i_u})"/>
</effect>
</case>
<case>
<condition>
<if var="i_u" value="Release"/>
<if var="perceived" value="BlueObj" relation="in"/>
<if var="carried" value="[]" relation="!="/>
</condition>
<effect util="theta(i_u=release^perceived=blueobj^carried=yes)">
<set var="a_m" value="Do(Release)"/>
</effect>
<effect util="theta(i_u=release^perceived=blueobj^carried=yes^a_m=Confirm)">
<set var="a_m" value="Confirm({i_u})"/>
</effect>
</case>
<case>
<condition>
<if var="i_u" value="Release"/>
<if var="perceived" value="BlueObj" relation="in"/>
<if var="carried" value="[]"/>
</condition>
<effect util="theta(i_u=release^perceived=blueobj^carried=no)">
<set var="a_m" value="Say(DoNotCarryObject)"/>
</effect>
<effect util="theta(i_u=release^perceived=blueobj^carried=no^a_m=Confirm)">
<set var="a_m" value="Confirm({i_u})"/>
</effect>
</case>
<case>
<condition>
<if var="i_u" value="WhatDoYouSee"/>
<if var="perceived" value="[]"/>
<if var="carried" value="[]" relation="!="/>
</condition>
<effect util="theta(i_u=whatdoyousee^perceived=nothing^carried=yes)">
<set var="a_m" value="Describe({perceived})"/>
</effect>
</case>
<case>
<condition>
<if var="i_u" value="WhatDoYouSee"/>
<if var="perceived" value="[]"/>
<if var="carried" value="[]"/>
</condition>
<effect util="theta(i_u=whatdoyousee^perceived=nothing^carried=no)">
<set var="a_m" value="Describe({perceived})"/>
</effect>
</case>
<case>
<condition>
<if var="i_u" value="WhatDoYouSee"/>
<if var="perceived" value="RedObj" relation="in"/>
<if var="carried" value="[]" relation="!="/>
</condition>
<effect util="theta(i_u=whatdoyousee^perceived=redobj^carried=yes)">
<set var="a_m" value="Describe({perceived})"/>
</effect>
</case>
<case>
<condition>
<if var="i_u" value="WhatDoYouSee"/>
<if var="perceived" value="RedObj" relation="in"/>
<if var="carried" value="[]"/>
</condition>
<effect util="theta(i_u=whatdoyousee^perceived=redobj^carried=no)">
<set var="a_m" value="Describe({perceived})"/>
</effect>
</case>
<case>
<condition>
<if var="i_u" value="WhatDoYouSee"/>
<if var="perceived" value="BlueObj" relation="in"/>
<if var="carried" value="[]" relation="!="/>
</condition>
<effect util="theta(i_u=whatdoyousee^perceived=blueobj^carried=yes)">
<set var="a_m" value="Describe({perceived})"/>
</effect>
</case>
<case>
<condition>
<if var="i_u" value="WhatDoYouSee"/>
<if var="perceived" value="BlueObj" relation="in"/>
<if var="carried" value="[]"/>
</condition>
<effect util="theta(i_u=whatdoyousee^perceived=blueobj^carried=no)">
<set var="a_m" value="Describe({perceived})"/>
</effect>
</case>
<case>
<condition>
<if var="i_u" value="DoYouSee(RedObj)"/>
<if var="perceived" value="[]"/>
<if var="carried" value="[]" relation="!="/>
</condition>
<effect util="theta(i_u=doyousee(redobj)^perceived=nothing^carried=yes)">
<set var="a_m" value="Say(Disconfirm)"/>
</effect>
</case>
<case>
<condition>
<if var="i_u" value="DoYouSee(RedObj)"/>
<if var="perceived" value="[]"/>
<if var="carried" value="[]"/>
</condition>
<effect util="theta(i_u=doyousee(redobj)^perceived=nothing^carried=no)">
<set var="a_m" value="Say(Disconfirm)"/>
</effect>
</case>
<case>
<condition>
<if var="i_u" value="DoYouSee(RedObj)"/>
<if var="perceived" value="RedObj" relation="in"/>
<if var="carried" value="[]" relation="!="/>
</condition>
<effect util="theta(i_u=doyousee(redobj)^perceived=redobj^carried=yes)">
<set var="a_m" value="Say(Confirm)"/>
</effect>
</case>
<case>
<condition>
<if var="i_u" value="DoYouSee(RedObj)"/>
<if var="perceived" value="RedObj" relation="in"/>
<if var="carried" value="[]"/>
</condition>
<effect util="theta(i_u=doyousee(redobj)^perceived=redobj^carried=no)">
<set var="a_m" value="Say(Confirm)"/>
</effect>
</case>
<case>
<condition>
<if var="i_u" value="DoYouSee(RedObj)"/>
<if var="perceived" value="BlueObj" relation="in"/>
<if var="carried" value="[]" relation="!="/>
</condition>
<effect util="theta(i_u=doyousee(redobj)^perceived=blueobj^carried=yes)">
<set var="a_m" value="Say(Disconfirm)"/>
</effect>
</case>
<case>
<condition>
<if var="i_u" value="DoYouSee(RedObj)"/>
<if var="perceived" value="BlueObj" relation="in"/>
<if var="carried" value="[]"/>
</condition>
<effect util="theta(i_u=doyousee(redobj)^perceived=blueobj^carried=no)">
<set var="a_m" value="Say(Disconfirm)"/>
</effect>
</case>
<case>
<condition>
<if var="i_u" value="DoYouSee(BlueObj)"/>
<if var="perceived" value="[]"/>
<if var="carried" value="[]" relation="!="/>
</condition>
<effect util="theta(i_u=doyousee(blueobj)^perceived=nothing^carried=yes)">
<set var="a_m" value="Say(Disconfirm)"/>
</effect>
</case>
<case>
<condition>
<if var="i_u" value="DoYouSee(BlueObj)"/>
<if var="perceived" value="[]"/>
<if var="carried" value="[]"/>
</condition>
<effect util="theta(i_u=doyousee(blueobj)^perceived=nothing^carried=no)">
<set var="a_m" value="Say(Disconfirm)"/>
</effect>
</case>
<case>
<condition>
<if var="i_u" value="DoYouSee(BlueObj)"/>
<if var="perceived" value="RedObj" relation="in"/>
<if var="carried" value="[]" relation="!="/>
</condition>
<effect util="theta(i_u=doyousee(blueobj)^perceived=redobj^carried=yes)">
<set var="a_m" value="Say(Disconfirm)"/>
</effect>
</case>
<case>
<condition>
<if var="i_u" value="DoYouSee(BlueObj)"/>
<if var="perceived" value="RedObj" relation="in"/>
<if var="carried" value="[]"/>
</condition>
<effect util="theta(i_u=doyousee(blueobj)^perceived=redobj^carried=no)">
<set var="a_m" value="Say(Disconfirm)"/>
</effect>
</case>
<case>
<condition>
<if var="i_u" value="DoYouSee(BlueObj)"/>
<if var="perceived" value="BlueObj" relation="in"/>
<if var="carried" value="[]" relation="!="/>
</condition>
<effect util="theta(i_u=doyousee(blueobj)^perceived=blueobj^carried=yes)">
<set var="a_m" value="Say(Confirm)"/>
</effect>
</case>
<case>
<condition>
<if var="i_u" value="DoYouSee(BlueObj)"/>
<if var="perceived" value="BlueObj" relation="in"/>
<if var="carried" value="[]"/>
</condition>
<effect util="theta(i_u=doyousee(blueobj)^perceived=blueobj^carried=no)">
<set var="a_m" value="Say(Confirm)"/>
</effect>
</case>
<case>
<condition>
<if var="i_u" value="Greeting"/>
<if var="perceived" value="[]"/>
<if var="carried" value="[]" relation="!="/>
</condition>
<effect util="theta(i_u=greeting^perceived=nothing^carried=yes)">
<set var="a_m" value="Say(Greet)"/>
</effect>
</case>
<case>
<condition>
<if var="i_u" value="Greeting"/>
<if var="perceived" value="[]"/>
<if var="carried" value="[]"/>
</condition>
<effect util="theta(i_u=greeting^perceived=nothing^carried=no)">
<set var="a_m" value="Say(Greet)"/>
</effect>
</case>
<case>
<condition>
<if var="i_u" value="Greeting"/>
<if var="perceived" value="RedObj" relation="in"/>
<if var="carried" value="[]" relation="!="/>
</condition>
<effect util="theta(i_u=greeting^perceived=redobj^carried=yes)">
<set var="a_m" value="Say(Greet)"/>
</effect>
</case>
<case>
<condition>
<if var="i_u" value="Greeting"/>
<if var="perceived" value="RedObj" relation="in"/>
<if var="carried" value="[]"/>
</condition>
<effect util="theta(i_u=greeting^perceived=redobj^carried=no)">
<set var="a_m" value="Say(Greet)"/>
</effect>
</case>
<case>
<condition>
<if var="i_u" value="Greeting"/>
<if var="perceived" value="BlueObj" relation="in"/>
<if var="carried" value="[]" relation="!="/>
</condition>
<effect util="theta(i_u=greeting^perceived=blueobj^carried=yes)">
<set var="a_m" value="Say(Greet)"/>
</effect>
</case>
<case>
<condition>
<if var="i_u" value="Greeting"/>
<if var="perceived" value="BlueObj" relation="in"/>
<if var="carried" value="[]"/>
</condition>
<effect util="theta(i_u=greeting^perceived=blueobj^carried=no)">
<set var="a_m" value="Say(Greet)"/>
</effect>
</case>
<case>
<condition>
<if var="i_u" value="Closing"/>
<if var="perceived" value="[]"/>
<if var="carried" value="[]" relation="!="/>
</condition>
<effect util="theta(i_u=closing^perceived=nothing^carried=yes)">
<set var="a_m" value="Say(Goodbye)"/>
</effect>
</case>
<case>
<condition>
<if var="i_u" value="Closing"/>
<if var="perceived" value="[]"/>
<if var="carried" value="[]"/>
</condition>
<effect util="theta(i_u=closing^perceived=nothing^carried=no)">
<set var="a_m" value="Say(Goodbye)"/>
</effect>
</case>
<case>
<condition>
<if var="i_u" value="Closing"/>
<if var="perceived" value="RedObj" relation="in"/>
<if var="carried" value="[]" relation="!="/>
</condition>
<effect util="theta(i_u=closing^perceived=redobj^carried=yes)">
<set var="a_m" value="Say(Goodbye)"/>
</effect>
</case>
<case>
<condition>
<if var="i_u" value="Closing"/>
<if var="perceived" value="RedObj" relation="in"/>
<if var="carried" value="[]"/>
</condition>
<effect util="theta(i_u=closing^perceived=redobj^carried=no)">
<set var="a_m" value="Say(Goodbye)"/>
</effect>
</case>
<case>
<condition>
<if var="i_u" value="Closing"/>
<if var="perceived" value="BlueObj" relation="in"/>
<if var="carried" value="[]" relation="!="/>
</condition>
<effect util="theta(i_u=closing^perceived=blueobj^carried=yes)">
<set var="a_m" value="Say(Goodbye)"/>
</effect>
</case>
<case>
<condition>
<if var="i_u" value="Closing"/>
<if var="perceived" value="BlueObj" relation="in"/>
<if var="carried" value="[]"/>
</condition>
<effect util="theta(i_u=closing^perceived=blueobj^carried=no)">
<set var="a_m" value="Say(Goodbye)"/>
</effect>
</case>
<case>
<condition>
<if var="i_u" value="Ask(Name)"/>
<if var="perceived" value="[]"/>
<if var="carried" value="[]" relation="!="/>
</condition>
<effect util="theta(i_u=ask(name)^perceived=nothing^carried=yes)">
<set var="a_m" value="Say(NameIsLenny)"/>
</effect>
</case>
<case>
<condition>
<if var="i_u" value="Ask(Name)"/>
<if var="perceived" value="[]"/>
<if var="carried" value="[]"/>
</condition>
<effect util="theta(i_u=ask(name)^perceived=nothing^carried=no)">
<set var="a_m" value="Say(NameIsLenny)"/>
</effect>
</case>
<case>
<condition>
<if var="i_u" value="Ask(Name)"/>
<if var="perceived" value="RedObj" relation="in"/>
<if var="carried" value="[]" relation="!="/>
</condition>
<effect util="theta(i_u=ask(name)^perceived=redobj^carried=yes)">
<set var="a_m" value="Say(NameIsLenny)"/>
</effect>
</case>
<case>
<condition>
<if var="i_u" value="Ask(Name)"/>
<if var="perceived" value="RedObj" relation="in"/>
<if var="carried" value="[]"/>
</condition>
<effect util="theta(i_u=ask(name)^perceived=redobj^carried=no)">
<set var="a_m" value="Say(NameIsLenny)"/>
</effect>
</case>
<case>
<condition>
<if var="i_u" value="Ask(Name)"/>
<if var="perceived" value="BlueObj" relation="in"/>
<if var="carried" value="[]" relation="!="/>
</condition>
<effect util="theta(i_u=ask(name)^perceived=blueobj^carried=yes)">
<set var="a_m" value="Say(NameIsLenny)"/>
</effect>
</case>
<case>
<condition>
<if var="i_u" value="Ask(Name)"/>
<if var="perceived" value="BlueObj" relation="in"/>
<if var="carried" value="[]"/>
</condition>
<effect util="theta(i_u=ask(name)^perceived=blueobj^carried=no)">
<set var="a_m" value="Say(NameIsLenny)"/>
</effect>
</case>

</rule>

<rule>
<case>
<condition>
<if var="a_u" value="Move(Left)"/>
<if var="motion" value="true"/>
</condition>
<effect util="theta(motion=true^a_u=Move(Left)^a_m=AskRepeat)">
<set var="a_m" value="AskRepeat"/>
</effect>
<effect util="theta(motion=true^a_u=Move(Left)^a_m=Do(Stop))">
<set var="a_m" value="Do(Stop)"/>
</effect>
</case>
<case>
<condition>
<if var="a_u" value="Move(Left)"/>
<if var="motion" value="None"/>
</condition>
<effect util="theta(motion=None^a_u=Move(Left)^a_m=AskRepeat)">
<set var="a_m" value="AskRepeat"/>
</effect>
<effect util="theta(motion=None^a_u=Move(Left)^a_m=Do(Stop))">
<set var="a_m" value="Do(Stop)"/>
</effect>
</case>
<case>
<condition>
<if var="a_u" value="Move(Right)"/>
<if var="motion" value="true"/>
</condition>
<effect util="theta(motion=true^a_u=Move(Right)^a_m=AskRepeat)">
<set var="a_m" value="AskRepeat"/>
</effect>
<effect util="theta(motion=true^a_u=Move(Right)^a_m=Do(Stop))">
<set var="a_m" value="Do(Stop)"/>
</effect>
</case>
<case>
<condition>
<if var="a_u" value="Move(Right)"/>
<if var="motion" value="None"/>
</condition>
<effect util="theta(motion=None^a_u=Move(Right)^a_m=AskRepeat)">
<set var="a_m" value="AskRepeat"/>
</effect>
<effect util="theta(motion=None^a_u=Move(Right)^a_m=Do(Stop))">
<set var="a_m" value="Do(Stop)"/>
</effect>
</case>
<case>
<condition>
<if var="a_u" value="Move(Forward)"/>
<if var="motion" value="true"/>
</condition>
<effect util="theta(motion=true^a_u=Move(Forward)^a_m=AskRepeat)">
<set var="a_m" value="AskRepeat"/>
</effect>
<effect util="theta(motion=true^a_u=Move(Forward)^a_m=Do(Stop))">
<set var="a_m" value="Do(Stop)"/>
</effect>
</case>
<case>
<condition>
<if var="a_u" value="Move(Forward)"/>
<if var="motion" value="None"/>
</condition>
<effect util="theta(motion=None^a_u=Move(Forward)^a_m=AskRepeat)">
<set var="a_m" value="AskRepeat"/>
</effect>
<effect util="theta(motion=None^a_u=Move(Forward)^a_m=Do(Stop))">
<set var="a_m" value="Do(Stop)"/>
</effect>
</case>
<case>
<condition>
<if var="a_u" value="Move(Backward)"/>
<if var="motion" value="true"/>
</condition>
<effect util="theta(motion=true^a_u=Move(Backward)^a_m=AskRepeat)">
<set var="a_m" value="AskRepeat"/>
</effect>
<effect util="theta(motion=true^a_u=Move(Backward)^a_m=Do(Stop))">
<set var="a_m" value="Do(Stop)"/>
</effect>
</case>
<case>
<condition>
<if var="a_u" value="Move(Backward)"/>
<if var="motion" value="None"/>
</condition>
<effect util="theta(motion=None^a_u=Move(Backward)^a_m=AskRepeat)">
<set var="a_m" value="AskRepeat"/>
</effect>
<effect util="theta(motion=None^a_u=Move(Backward)^a_m=Do(Stop))">
<set var="a_m" value="Do(Stop)"/>
</effect>
</case>
<case>
<condition>
<if var="a_u" value="Move(Turn)"/>
<if var="motion" value="true"/>
</condition>
<effect util="theta(motion=true^a_u=Move(Turn)^a_m=AskRepeat)">
<set var="a_m" value="AskRepeat"/>
</effect>
<effect util="theta(motion=true^a_u=Move(Turn)^a_m=Do(Stop))">
<set var="a_m" value="Do(Stop)"/>
</effect>
</case>
<case>
<condition>
<if var="a_u" value="Move(Turn)"/>
<if var="motion" value="None"/>
</condition>
<effect util="theta(motion=None^a_u=Move(Turn)^a_m=AskRepeat)">
<set var="a_m" value="AskRepeat"/>
</effect>
<effect util="theta(motion=None^a_u=Move(Turn)^a_m=Do(Stop))">
<set var="a_m" value="Do(Stop)"/>
</effect>
</case>
<case>
<condition>
<if var="a_u" value="Move(Left,Short)"/>
<if var="motion" value="true"/>
</condition>
<effect util="theta(motion=true^a_u=Move(Left,Short)^a_m=AskRepeat)">
<set var="a_m" value="AskRepeat"/>
</effect>
<effect util="theta(motion=true^a_u=Move(Left,Short)^a_m=Do(Stop))">
<set var="a_m" value="Do(Stop)"/>
</effect>
</case>
<case>
<condition>
<if var="a_u" value="Move(Left,Short)"/>
<if var="motion" value="None"/>
</condition>
<effect util="theta(motion=None^a_u=Move(Left,Short)^a_m=AskRepeat)">
<set var="a_m" value="AskRepeat"/>
</effect>
<effect util="theta(motion=None^a_u=Move(Left,Short)^a_m=Do(Stop))">
<set var="a_m" value="Do(Stop)"/>
</effect>
</case>
<case>
<condition>
<if var="a_u" value="Move(Right,Short)"/>
<if var="motion" value="true"/>
</condition>
<effect util="theta(motion=true^a_u=Move(Right,Short)^a_m=AskRepeat)">
<set var="a_m" value="AskRepeat"/>
</effect>
<effect util="theta(motion=true^a_u=Move(Right,Short)^a_m=Do(Stop))">
<set var="a_m" value="Do(Stop)"/>
</effect>
</case>
<case>
<condition>
<if var="a_u" value="Move(Right,Short)"/>
<if var="motion" value="None"/>
</condition>
<effect util="theta(motion=None^a_u=Move(Right,Short)^a_m=AskRepeat)">
<set var="a_m" value="AskRepeat"/>
</effect>
<effect util="theta(motion=None^a_u=Move(Right,Short)^a_m=Do(Stop))">
<set var="a_m" value="Do(Stop)"/>
</effect>
</case>
<case>
<condition>
<if var="a_u" value="Move(Forward,Short)"/>
<if var="motion" value="true"/>
</condition>
<effect util="theta(motion=true^a_u=Move(Forward,Short)^a_m=AskRepeat)">
<set var="a_m" value="AskRepeat"/>
</effect>
<effect util="theta(motion=true^a_u=Move(Forward,Short)^a_m=Do(Stop))">
<set var="a_m" value="Do(Stop)"/>
</effect>
</case>
<case>
<condition>
<if var="a_u" value="Move(Forward,Short)"/>
<if var="motion" value="None"/>
</condition>
<effect util="theta(motion=None^a_u=Move(Forward,Short)^a_m=AskRepeat)">
<set var="a_m" value="AskRepeat"/>
</effect>
<effect util="theta(motion=None^a_u=Move(Forward,Short)^a_m=Do(Stop))">
<set var="a_m" value="Do(Stop)"/>
</effect>
</case>
<case>
<condition>
<if var="a_u" value="Move(Backward,Short)"/>
<if var="motion" value="true"/>
</condition>
<effect util="theta(motion=true^a_u=Move(Backward,Short)^a_m=AskRepeat)">
<set var="a_m" value="AskRepeat"/>
</effect>
<effect util="theta(motion=true^a_u=Move(Backward,Short)^a_m=Do(Stop))">
<set var="a_m" value="Do(Stop)"/>
</effect>
</case>
<case>
<condition>
<if var="a_u" value="Move(Backward,Short)"/>
<if var="motion" value="None"/>
</condition>
<effect util="theta(motion=None^a_u=Move(Backward,Short)^a_m=AskRepeat)">
<set var="a_m" value="AskRepeat"/>
</effect>
<effect util="theta(motion=None^a_u=Move(Backward,Short)^a_m=Do(Stop))">
<set var="a_m" value="Do(Stop)"/>
</effect>
</case>
<case>
<condition>
<if var="a_u" value="PickUp(RedObj)"/>
<if var="motion" value="true"/>
</condition>
<effect util="theta(motion=true^a_u=PickUp(RedObj)^a_m=AskRepeat)">
<set var="a_m" value="AskRepeat"/>
</effect>
<effect util="theta(motion=true^a_u=PickUp(RedObj)^a_m=Do(Stop))">
<set var="a_m" value="Do(Stop)"/>
</effect>
</case>
<case>
<condition>
<if var="a_u" value="PickUp(RedObj)"/>
<if var="motion" value="None"/>
</condition>
<effect util="theta(motion=None^a_u=PickUp(RedObj)^a_m=AskRepeat)">
<set var="a_m" value="AskRepeat"/>
</effect>
<effect util="theta(motion=None^a_u=PickUp(RedObj)^a_m=Do(Stop))">
<set var="a_m" value="Do(Stop)"/>
</effect>
</case>
<case>
<condition>
<if var="a_u" value="PickUp(BlueObj)"/>
<if var="motion" value="true"/>
</condition>
<effect util="theta(motion=true^a_u=PickUp(BlueObj)^a_m=AskRepeat)">
<set var="a_m" value="AskRepeat"/>
</effect>
<effect util="theta(motion=true^a_u=PickUp(BlueObj)^a_m=Do(Stop))">
<set var="a_m" value="Do(Stop)"/>
</effect>
</case>
<case>
<condition>
<if var="a_u" value="PickUp(BlueObj)"/>
<if var="motion" value="None"/>
</condition>
<effect util="theta(motion=None^a_u=PickUp(BlueObj)^a_m=AskRepeat)">
<set var="a_m" value="AskRepeat"/>
</effect>
<effect util="theta(motion=None^a_u=PickUp(BlueObj)^a_m=Do(Stop))">
<set var="a_m" value="Do(Stop)"/>
</effect>
</case>
<case>
<condition>
<if var="a_u" value="PickUp(AtFeet)"/>
<if var="motion" value="true"/>
</condition>
<effect util="theta(motion=true^a_u=PickUp(AtFeet)^a_m=AskRepeat)">
<set var="a_m" value="AskRepeat"/>
</effect>
<effect util="theta(motion=true^a_u=PickUp(AtFeet)^a_m=Do(Stop))">
<set var="a_m" value="Do(Stop)"/>
</effect>
</case>
<case>
<condition>
<if var="a_u" value="PickUp(AtFeet)"/>
<if var="motion" value="None"/>
</condition>
<effect util="theta(motion=None^a_u=PickUp(AtFeet)^a_m=AskRepeat)">
<set var="a_m" value="AskRepeat"/>
</effect>
<effect util="theta(motion=None^a_u=PickUp(AtFeet)^a_m=Do(Stop))">
<set var="a_m" value="Do(Stop)"/>
</effect>
</case>
<case>
<condition>
<if var="a_u" value="PickUp(Other)"/>
<if var="motion" value="true"/>
</condition>
<effect util="theta(motion=true^a_u=PickUp(Other)^a_m=AskRepeat)">
<set var="a_m" value="AskRepeat"/>
</effect>
<effect util="theta(motion=true^a_u=PickUp(Other)^a_m=Do(Stop))">
<set var="a_m" value="Do(Stop)"/>
</effect>
</case>
<case>
<condition>
<if var="a_u" value="PickUp(Other)"/>
<if var="motion" value="None"/>
</condition>
<effect util="theta(motion=None^a_u=PickUp(Other)^a_m=AskRepeat)">
<set var="a_m" value="AskRepeat"/>
</effect>
<effect util="theta(motion=None^a_u=PickUp(Other)^a_m=Do(Stop))">
<set var="a_m" value="Do(Stop)"/>
</effect>
</case>
<case>
<condition>
<if var="a_u" value="Release"/>
<if var="motion" value="true"/>
</condition>
<effect util="theta(motion=true^a_u=Release^a_m=AskRepeat)">
<set var="a_m" value="AskRepeat"/>
</effect>
<effect util="theta(motion=true^a_u=Release^a_m=Do(Stop))">
<set var="a_m" value="Do(Stop)"/>
</effect>
</case>
<case>
<condition>
<if var="a_u" value="Release"/>
<if var="motion" value="None"/>
</condition>
<effect util="theta(motion=None^a_u=Release^a_m=AskRepeat)">
<set var="a_m" value="AskRepeat"/>
</effect>
<effect util="theta(motion=None^a_u=Release^a_m=Do(Stop))">
<set var="a_m" value="Do(Stop)"/>
</effect>
</case>
<case>
<condition>
<if var="a_u" value="WhatDoYouSee"/>
<if var="motion" value="true"/>
</condition>
<effect util="theta(motion=true^a_u=WhatDoYouSee^a_m=AskRepeat)">
<set var="a_m" value="AskRepeat"/>
</effect>
<effect util="theta(motion=true^a_u=WhatDoYouSee^a_m=Do(Stop))">
<set var="a_m" value="Do(Stop)"/>
</effect>
</case>
<case>
<condition>
<if var="a_u" value="WhatDoYouSee"/>
<if var="motion" value="None"/>
</condition>
<effect util="theta(motion=None^a_u=WhatDoYouSee^a_m=AskRepeat)">
<set var="a_m" value="AskRepeat"/>
</effect>
<effect util="theta(motion=None^a_u=WhatDoYouSee^a_m=Do(Stop))">
<set var="a_m" value="Do(Stop)"/>
</effect>
</case>
<case>
<condition>
<if var="a_u" value="DoYouSee(RedObj)"/>
<if var="motion" value="true"/>
</condition>
<effect util="theta(motion=true^a_u=DoYouSee(RedObj)^a_m=AskRepeat)">
<set var="a_m" value="AskRepeat"/>
</effect>
<effect util="theta(motion=true^a_u=DoYouSee(RedObj)^a_m=Do(Stop))">
<set var="a_m" value="Do(Stop)"/>
</effect>
</case>
<case>
<condition>
<if var="a_u" value="DoYouSee(RedObj)"/>
<if var="motion" value="None"/>
</condition>
<effect util="theta(motion=None^a_u=DoYouSee(RedObj)^a_m=AskRepeat)">
<set var="a_m" value="AskRepeat"/>
</effect>
<effect util="theta(motion=None^a_u=DoYouSee(RedObj)^a_m=Do(Stop))">
<set var="a_m" value="Do(Stop)"/>
</effect>
</case>
<case>
<condition>
<if var="a_u" value="DoYouSee(BlueObj)"/>
<if var="motion" value="true"/>
</condition>
<effect util="theta(motion=true^a_u=DoYouSee(BlueObj)^a_m=AskRepeat)">
<set var="a_m" value="AskRepeat"/>
</effect>
<effect util="theta(motion=true^a_u=DoYouSee(BlueObj)^a_m=Do(Stop))">
<set var="a_m" value="Do(Stop)"/>
</effect>
</case>
<case>
<condition>
<if var="a_u" value="DoYouSee(BlueObj)"/>
<if var="motion" value="None"/>
</condition>
<effect util="theta(motion=None^a_u=DoYouSee(BlueObj)^a_m=AskRepeat)">
<set var="a_m" value="AskRepeat"/>
</effect>
<effect util="theta(motion=None^a_u=DoYouSee(BlueObj)^a_m=Do(Stop))">
<set var="a_m" value="Do(Stop)"/>
</effect>
</case>
<case>
<condition>
<if var="a_u" value="Greeting"/>
<if var="motion" value="true"/>
</condition>
<effect util="theta(motion=true^a_u=Greeting^a_m=AskRepeat)">
<set var="a_m" value="AskRepeat"/>
</effect>
<effect util="theta(motion=true^a_u=Greeting^a_m=Do(Stop))">
<set var="a_m" value="Do(Stop)"/>
</effect>
</case>
<case>
<condition>
<if var="a_u" value="Greeting"/>
<if var="motion" value="None"/>
</condition>
<effect util="theta(motion=None^a_u=Greeting^a_m=AskRepeat)">
<set var="a_m" value="AskRepeat"/>
</effect>
<effect util="theta(motion=None^a_u=Greeting^a_m=Do(Stop))">
<set var="a_m" value="Do(Stop)"/>
</effect>
</case>
<case>
<condition>
<if var="a_u" value="Closing"/>
<if var="motion" value="true"/>
</condition>
<effect util="theta(motion=true^a_u=Closing^a_m=AskRepeat)">
<set var="a_m" value="AskRepeat"/>
</effect>
<effect util="theta(motion=true^a_u=Closing^a_m=Do(Stop))">
<set var="a_m" value="Do(Stop)"/>
</effect>
</case>
<case>
<condition>
<if var="a_u" value="Closing"/>
<if var="motion" value="None"/>
</condition>
<effect util="theta(motion=None^a_u=Closing^a_m=AskRepeat)">
<set var="a_m" value="AskRepeat"/>
</effect>
<effect util="theta(motion=None^a_u=Closing^a_m=Do(Stop))">
<set var="a_m" value="Do(Stop)"/>
</effect>
</case>
<case>
<condition>
<if var="a_u" value="Ask(Name)"/>
<if var="motion" value="true"/>
</condition>
<effect util="theta(motion=true^a_u=Ask(Name)^a_m=AskRepeat)">
<set var="a_m" value="AskRepeat"/>
</effect>
<effect util="theta(motion=true^a_u=Ask(Name)^a_m=Do(Stop))">
<set var="a_m" value="Do(Stop)"/>
</effect>
</case>
<case>
<condition>
<if var="a_u" value="Ask(Name)"/>
<if var="motion" value="None"/>
</condition>
<effect util="theta(motion=None^a_u=Ask(Name)^a_m=AskRepeat)">
<set var="a_m" value="AskRepeat"/>
</effect>
<effect util="theta(motion=None^a_u=Ask(Name)^a_m=Do(Stop))">
<set var="a_m" value="Do(Stop)"/>
</effect>
</case>
<case>
<condition>
<if var="a_u" value="RepeatLast"/>
<if var="motion" value="true"/>
</condition>
<effect util="theta(motion=true^a_u=RepeatLast^a_m=AskRepeat)">
<set var="a_m" value="AskRepeat"/>
</effect>
<effect util="theta(motion=true^a_u=RepeatLast^a_m=Do(Stop))">
<set var="a_m" value="Do(Stop)"/>
</effect>
</case>
<case>
<condition>
<if var="a_u" value="RepeatLast"/>
<if var="motion" value="None"/>
</condition>
<effect util="theta(motion=None^a_u=RepeatLast^a_m=AskRepeat)">
<set var="a_m" value="AskRepeat"/>
</effect>
<effect util="theta(motion=None^a_u=RepeatLast^a_m=Do(Stop))">
<set var="a_m" value="Do(Stop)"/>
</effect>
</case>
<case>
<condition>
<if var="a_u" value="Stop"/>
<if var="motion" value="true"/>
</condition>
<effect util="theta(motion=true^a_u=Stop^a_m=AskRepeat)">
<set var="a_m" value="AskRepeat"/>
</effect>
<effect util="theta(motion=true^a_u=Stop^a_m=Do(Stop))">
<set var="a_m" value="Do(Stop)"/>
</effect>
</case>
<case>
<condition>
<if var="a_u" value="Stop"/>
<if var="motion" value="None"/>
</condition>
<effect util="theta(motion=None^a_u=Stop^a_m=AskRepeat)">
<set var="a_m" value="AskRepeat"/>
</effect>
<effect util="theta(motion=None^a_u=Stop^a_m=Do(Stop))">
<set var="a_m" value="Do(Stop)"/>
</effect>
</case>
<case>
<condition>
<if var="a_u" value="Confirm"/>
<if var="motion" value="true"/>
</condition>
<effect util="theta(motion=true^a_u=Confirm^a_m=AskRepeat)">
<set var="a_m" value="AskRepeat"/>
</effect>
<effect util="theta(motion=true^a_u=Confirm^a_m=Do(Stop))">
<set var="a_m" value="Do(Stop)"/>
</effect>
</case>
<case>
<condition>
<if var="a_u" value="Confirm"/>
<if var="motion" value="None"/>
</condition>
<effect util="theta(motion=None^a_u=Confirm^a_m=AskRepeat)">
<set var="a_m" value="AskRepeat"/>
</effect>
<effect util="theta(motion=None^a_u=Confirm^a_m=Do(Stop))">
<set var="a_m" value="Do(Stop)"/>
</effect>
</case>
<case>
<condition>
<if var="a_u" value="Disconfirm"/>
<if var="motion" value="true"/>
</condition>
<effect util="theta(motion=true^a_u=Disconfirm^a_m=AskRepeat)">
<set var="a_m" value="AskRepeat"/>
</effect>
<effect util="theta(motion=true^a_u=Disconfirm^a_m=Do(Stop))">
<set var="a_m" value="Do(Stop)"/>
</effect>
</case>
<case>
<condition>
<if var="a_u" value="Disconfirm"/>
<if var="motion" value="None"/>
</condition>
<effect util="theta(motion=None^a_u=Disconfirm^a_m=AskRepeat)">
<set var="a_m" value="AskRepeat"/>
</effect>
<effect util="theta(motion=None^a_u=Disconfirm^a_m=Do(Stop))">
<set var="a_m" value="Do(Stop)"/>
</effect>
</case>
<case>
<condition>
<if var="a_u" value="Grounding"/>
<if var="motion" value="true"/>
</condition>
<effect util="theta(motion=true^a_u=Grounding^a_m=AskRepeat)">
<set var="a_m" value="AskRepeat"/>
</effect>
<effect util="theta(motion=true^a_u=Grounding^a_m=Do(Stop))">
<set var="a_m" value="Do(Stop)"/>
</effect>
</case>
<case>
<condition>
<if var="a_u" value="Grounding"/>
<if var="motion" value="None"/>
</condition>
<effect util="theta(motion=None^a_u=Grounding^a_m=AskRepeat)">
<set var="a_m" value="AskRepeat"/>
</effect>
<effect util="theta(motion=None^a_u=Grounding^a_m=Do(Stop))">
<set var="a_m" value="Do(Stop)"/>
</effect>
</case>
<case>
<condition>
<if var="a_u" value="None"/>
<if var="motion" value="true"/>
</condition>
<effect util="theta(motion=true^a_u=None^a_m=AskRepeat)">
<set var="a_m" value="AskRepeat"/>
</effect>
<effect util="theta(motion=true^a_u=None^a_m=Do(Stop))">
<set var="a_m" value="Do(Stop)"/>
</effect>
</case>
<case>
<condition>
<if var="a_u" value="None"/>
<if var="motion" value="None"/>
</condition>
<effect util="theta(motion=None^a_u=None^a_m=AskRepeat)">
<set var="a_m" value="AskRepeat"/>
</effect>
<effect util="theta(motion=None^a_u=None^a_m=Do(Stop))">
<set var="a_m" value="Do(Stop)"/>
</effect>
</case>

</rule>
</model>
